{
  "version": "2.0",
  "lastUpdated": "2026-04-24T00:15:00.000Z",
  "activeFeatures": [],
  "primaryFeature": null,
  "features": {
    "irms-improvements": {
      "phase": "archived",
      "matchRate": 97.6,
      "updatedAt": "2026-03-08",
      "archivedTo": "docs/archive/2026-03/irms-improvements",
      "archivedAt": "2026-03-08",
      "documents": {
        "plan": "docs/archive/2026-03/irms-improvements/irms-improvements.plan.md",
        "design": "docs/archive/2026-03/irms-improvements/irms-improvements.design.md",
        "analysis": "docs/archive/2026-03/irms-improvements/irms-improvements.analysis.md",
        "report": "docs/archive/2026-03/irms-improvements/irms-improvements.report.md"
      },
      "status": {
        "plan": {
          "state": "completed",
          "lastModified": "2026-03-07"
        },
        "design": {
          "state": "completed",
          "lastModified": "2026-03-07"
        },
        "do": {
          "state": "completed",
          "lastModified": "2026-03-08"
        },
        "analysis": {
          "state": "completed",
          "lastModified": "2026-03-08"
        },
        "report": {
          "state": "completed",
          "lastModified": "2026-03-08"
        }
      }
    },
    "attendance-view": {
      "phase": "archived",
      "matchRate": 96,
      "updatedAt": "2026-04-23",
      "archivedTo": "docs/archive/2026-04/attendance-view",
      "archivedAt": "2026-04-23",
      "documents": {
        "plan": "docs/archive/2026-04/attendance-view/attendance-view.plan.md",
        "design": "docs/archive/2026-04/attendance-view/attendance-view.design.md",
        "analysis": "docs/archive/2026-04/attendance-view/attendance-view.analysis.md",
        "report": "docs/archive/2026-04/attendance-view/attendance-view.report.md"
      },
      "status": {
        "plan": {
          "state": "completed",
          "lastModified": "2026-04-23"
        },
        "design": {
          "state": "completed",
          "lastModified": "2026-04-23"
        },
        "do": {
          "state": "completed",
          "lastModified": "2026-04-23"
        },
        "analysis": {
          "state": "completed",
          "lastModified": "2026-04-23"
        },
        "report": {
          "state": "completed",
          "lastModified": "2026-04-23"
        }
      }
    },
    "attendance-alert": {
      "phase": "archived",
      "matchRate": 98,
      "updatedAt": "2026-04-24",
      "archivedTo": "docs/archive/2026-04/attendance-alert",
      "archivedAt": "2026-04-24",
      "documents": {
        "plan": "docs/archive/2026-04/attendance-alert/attendance-alert.plan.md",
        "design": "docs/archive/2026-04/attendance-alert/attendance-alert.design.md",
        "analysis": "docs/archive/2026-04/attendance-alert/attendance-alert.analysis.md",
        "report": "docs/archive/2026-04/attendance-alert/attendance-alert.report.md"
      },
      "status": {
        "plan": {
          "state": "completed",
          "lastModified": "2026-04-24"
        },
        "design": {
          "state": "completed",
          "lastModified": "2026-04-24"
        },
        "do": {
          "state": "completed",
          "lastModified": "2026-04-24"
        },
        "analysis": {
          "state": "completed",
          "lastModified": "2026-04-24"
        },
        "report": {
          "state": "completed",
          "lastModified": "2026-04-24"
        }
      }
    }
  },
  "pipeline": {
    "currentPhase": "archived",
    "level": "Dynamic",
    "phaseHistory": ["plan", "design", "do", "check", "completed"]
  },
  "session": {
    "startedAt": "2026-03-07T15:00:00.000Z",
    "onboardingCompleted": true,
    "lastActivity": "2026-04-24T00:15:00.000Z"
  },
  "history": []
}
